jijmodeling_transpiler-0.7.3.dist-info/RECORD
jijmodeling_transpiler-0.7.3.dist-info/WHEEL
jijmodeling_transpiler-0.7.3.dist-info/top_level.txt
jijmodeling_transpiler-0.7.3.dist-info/METADATA
jijmodeling_transpiler/__init__.cpython-312-darwin.so
jijmodeling_transpiler/__marker__.cpython-312-darwin.so
jijmodeling_transpiler/core/__init__.cpython-312-darwin.so
jijmodeling_transpiler/core/utils.cpython-312-darwin.so
jijmodeling_transpiler/core/variable_map.cpython-312-darwin.so
jijmodeling_transpiler/core/instance_data.cpython-312-darwin.so
jijmodeling_transpiler/core/mip/__init__.cpython-312-darwin.so
jijmodeling_transpiler/core/mip/to_mip.cpython-312-darwin.so
jijmodeling_transpiler/core/decode/__init__.cpython-312-darwin.so
jijmodeling_transpiler/core/decode/calc_value.cpython-312-darwin.so
jijmodeling_transpiler/core/decode/decode.cpython-312-darwin.so
jijmodeling_transpiler/core/decode/calc_energy.cpython-312-darwin.so
jijmodeling_transpiler/core/decode/evaluate.cpython-312-darwin.so
jijmodeling_transpiler/core/compile/__init__.cpython-312-darwin.so
jijmodeling_transpiler/core/compile/compile.cpython-312-darwin.so
jijmodeling_transpiler/core/compile/convert_to_substitutable.cpython-312-darwin.so
jijmodeling_transpiler/core/compile/trivial_constraint.cpython-312-darwin.so
jijmodeling_transpiler/core/compile/compiled_model.cpython-312-darwin.so
jijmodeling_transpiler/core/compile/partial_compile.cpython-312-darwin.so
jijmodeling_transpiler/core/compile/expand_forall.cpython-312-darwin.so
jijmodeling_transpiler/core/substitute/__init__.cpython-312-darwin.so
jijmodeling_transpiler/core/substitute/substitutable_convertion.cpython-312-darwin.so
jijmodeling_transpiler/core/substitute/substituted_repr.cpython-312-darwin.so
jijmodeling_transpiler/core/substitute/substitutable_expr/__init__.cpython-312-darwin.so
jijmodeling_transpiler/core/substitute/substitutable_expr/multi_operator.cpython-312-darwin.so
jijmodeling_transpiler/core/substitute/substitutable_expr/binary_operator.cpython-312-darwin.so
jijmodeling_transpiler/core/substitute/substitutable_expr/reduction_operator.cpython-312-darwin.so
