Metadata-Version: 2.2
Name: jijmodeling-transpiler
Version: 0.7.3
Home-page: https://www.jijzept.com
Author: Jij Inc.
Author-email: info@j-ij.com
License: Other/Proprietary License
Project-URL: Documentation, https://www.documentation.jijzept.com/docs/jijmodeling_docs/
Project-URL: Reference, https://www.ref.documentation.jijzept.com/jijmodeling-transpiler/
Project-URL: JijZept, https://pypi.org/project/jijzept/
Project-URL: JijModeling, https://pypi.org/project/jijmodeling/
Classifier: Programming Language :: Python :: 3.9
Classifier: Programming Language :: Python :: 3.10
Classifier: Programming Language :: Python :: 3.11
Classifier: Programming Language :: Python :: 3.12
Classifier: Programming Language :: Python :: 3 :: Only
Classifier: Programming Language :: Python :: Implementation :: CPython
Classifier: Operating System :: Microsoft :: Windows
Classifier: Operating System :: POSIX
Classifier: Operating System :: Unix
Classifier: Operating System :: MacOS
Requires-Python: <3.13,>=3.9
Requires-Dist: jijmodeling<2.0.0,>=1.0.0
Requires-Dist: numpy<1.27.0,>=1.17.0
Requires-Dist: typeguard
Requires-Dist: pydantic
Requires-Dist: pyqubo
Requires-Dist: mip
Requires-Dist: dimod
Provides-Extra: test
Requires-Dist: pytest; extra == "test"
Requires-Dist: pytest-cov; extra == "test"
Requires-Dist: pytest-randomly; extra == "test"
Requires-Dist: pytest-forked; extra == "test"
Requires-Dist: pytest-cython; extra == "test"
Requires-Dist: coverage; extra == "test"
Dynamic: provides-extra
